pilotlight_tools/__init__.py
pilotlight_tools/pl_build.py
pilotlight_tools-0.8.2.dist-info/METADATA
pilotlight_tools-0.8.2.dist-info/WHEEL
pilotlight_tools-0.8.2.dist-info/top_level.txt
pilotlight_tools-0.8.2.dist-info/RECORD
